pylint_af/__init__.py
pylint_af/main.py
pylint_af-1.0.3.dist-info/LICENSE
pylint_af-1.0.3.dist-info/METADATA
pylint_af-1.0.3.dist-info/WHEEL
pylint_af-1.0.3.dist-info/top_level.txt
pylint_af-1.0.3.dist-info/RECORD
