Metadata-Version: 2.1
Name: pylint-af
Version: 1.0.3
Summary: The package that allows you to check the Python code for compliance with PEP8.
Home-page: https://github.com/AlbertFarkhutdinov/pylint_af
Author: Albert Farkhutdinov
Author-email: albertfarhutdinov@gmail.com
License: UNKNOWN
Platform: UNKNOWN
Classifier: Development Status :: 5 - Production/Stable
Classifier: Programming Language :: Python :: 3.9
Classifier: License :: OSI Approved :: MIT License
Classifier: Operating System :: OS Independent
Requires-Python: >=3.6
License-File: LICENSE
Requires-Dist: pylint (<3,>=2)
